[
{"name":"netflix.tracing.zone0.client","size":1000,"edges":["netflix.tracing.zone0.load_balancer"]},
{"name":"netflix.tracing.zone0.load_balancer","size":1000,"edges":["netflix.tracing.zone0.nginx0","netflix.tracing.zone1.nginx0"]},
{"name":"netflix.tracing.zone0.nginx0","size":1000,"edges":["netflix.tracing.zone0.php-fpm0"]},
{"name":"netflix.tracing.zone0.php-fpm0","size":1000,"edges":["netflix.tracing.zone0.ReviewText0","netflix.tracing.zone0.AssignRating0","netflix.tracing.zone0.UniqueID0","netflix.tracing.zone0.MovieID0","netflix.tracing.zone0.MoviePlot0","netflix.tracing.zone0.MovieThumbnail0","netflix.tracing.zone0.MovieRating0","netflix.tracing.zone0.CastInfo0","netflix.tracing.zone0.WatchNext0","netflix.tracing.zone0.MovieReviews0","netflix.tracing.zone0.Photos0","netflix.tracing.zone0.Videos0","netflix.tracing.zone0.xapian0","netflix.tracing.zone0.MovieRecommendations0","netflix.tracing.zone0.Ads0"]},
{"name":"netflix.tracing.zone0.ReviewText0","size":1000,"edges":["netflix.tracing.zone0.ComposeReview0"]},
{"name":"netflix.tracing.zone0.AssignRating0","size":1000,"edges":["netflix.tracing.zone0.ComposeReview0"]},
{"name":"netflix.tracing.zone0.MovieID0","size":1000,"edges":["netflix.tracing.zone0.ComposeReview0"]},
{"name":"netflix.tracing.zone0.UniqueID0","size":1000,"edges":["netflix.tracing.zone0.ComposeReview0"]},
{"name":"netflix.tracing.zone0.MoviePlot0","size":1000,"edges":["netflix.tracing.zone0.ComposePage0"]},
{"name":"netflix.tracing.zone0.MovieThumbnail0","size":1000,"edges":["netflix.tracing.zone0.ComposePage0"]},
{"name":"netflix.tracing.zone0.MovieRating0","size":1000,"edges":["netflix.tracing.zone0.ComposePage0"]},
{"name":"netflix.tracing.zone0.CastInfo0","size":1000,"edges":["netflix.tracing.zone0.ComposePage0","netflix.tracing.zone0.memcached_castDB0"]},
{"name":"netflix.tracing.zone0.WatchNext0","size":1000,"edges":["netflix.tracing.zone0.ComposePage0"]},
{"name":"netflix.tracing.zone0.MovieReviews0","size":1000,"edges":["netflix.tracing.zone0.ComposePage0"]},
{"name":"netflix.tracing.zone0.Photos0","size":1000,"edges":["netflix.tracing.zone0.ComposePage0","netflix.tracing.zone0.memcached_photosDB0"]},
{"name":"netflix.tracing.zone0.Videos0","size":1000,"edges":["netflix.tracing.zone0.ComposePage0","netflix.tracing.zone0.VideosNFS0","netflix.tracing.zone0.memcached_videoPathDB0"]},
{"name":"netflix.tracing.zone0.Favorite0","size":1000,"edges":["netflix.tracing.zone0.WatchList0"]},
{"name":"netflix.tracing.zone0.Ads0","size":1000,"edges":["netflix.tracing.zone0.UserAccountInfo0","netflix.tracing.zone0.AdsUtilityMatrix0"]},
{"name":"netflix.tracing.zone0.AdsUtilityMatrix0","size":1000,"edges":["netflix.tracing.zone0.Ads0"]},
{"name":"netflix.tracing.zone0.memcached_ads_recommendations0","size":1000,"edges":["netflix.tracing.zone0.Ads0"]},
{"name":"netflix.tracing.zone0.WatchList0","size":1000,"edges":["netflix.tracing.zone0.Favorite0"]},
{"name":"netflix.tracing.zone0.MovieRecommendations0","size":1000,"edges":["netflix.tracing.zone0.MovieUtilityMatrix0"]},
{"name":"netflix.tracing.zone0.memcached_movies_recommendations0","size":1000,"edges":["netflix.tracing.zone0.MovieRecommendations0"]},
{"name":"netflix.tracing.zone0.xapian0","size":1000,"edges":["netflix.tracing.zone0.php-fpm0"]},
{"name":"netflix.tracing.zone0.MovieUtilityMatrix0","size":1000,"edges":["netflix.tracing.zone0.MovieRecommendations0"]},
{"name":"netflix.tracing.zone0.UserAccountInfo0","size":1000,"edges":["netflix.tracing.zone0.AccountLogin0"]},
{"name":"netflix.tracing.zone0.FavoriteStorage0","size":1000,"edges":["netflix.tracing.zone0.memcached_favorite0"]},
{"name":"netflix.tracing.zone0.memcached_favorite0","size":1000,"edges":["netflix.tracing.zone0.FavoriteStorage0"]},
{"name":"netflix.tracing.zone0.mongodb_favorite0","size":1000,"edges":["netflix.tracing.zone0.FavoriteStorage0"]},
{"name":"netflix.tracing.zone0.VideosNFS0","size":1000,"edges":["netflix.tracing.zone0.Videos0"]},
{"name":"netflix.tracing.zone0.RentMovie0","size":1000,"edges":["netflix.tracing.zone0.Payment0"]},
{"name":"netflix.tracing.zone0.VideoPlayer0","size":1000,"edges":["netflix.tracing.zone0.MoviesNFS0","netflix.tracing.zone0.memcached_movieDB0","netflix.tracing.zone0.mongodb_movieDB0","netflix.tracing.zone0.memcached_movieDB1","netflix.tracing.zone0.mongodb_movieDB1","netflix.tracing.zone0.memcached_movieDB2","netflix.tracing.zone0.mongodb_movieDB2","netflix.tracing.zone0.memcached_movieDB3","netflix.tracing.zone0.mongodb_movieDB3","netflix.tracing.zone0.memcached_movieDB4","netflix.tracing.zone0.mongodb_movieDB4","netflix.tracing.zone0.memcached_movieDB5","netflix.tracing.zone0.mongodb_movieDB5","netflix.tracing.zone0.memcached_movieDB6","netflix.tracing.zone0.mongodb_movieDB6","netflix.tracing.zone0.memcached_movieDB7","netflix.tracing.zone0.mongodb_movieDB7","netflix.tracing.zone0.memcached_movieDB8","netflix.tracing.zone0.mongodb_movieDB8","netflix.tracing.zone0.memcached_movieDB9"]},
{"name":"netflix.tracing.zone0.ComposeReview0","size":1000,"edges":["netflix.tracing.zone0.AccountLogin0","netflix.tracing.zone0.UserReviewDB0","netflix.tracing.zone0.MovieReviewDB0","netflix.tracing.zone0.ReviewStorage0"]},
{"name":"netflix.tracing.zone0.Payment0","size":1000,"edges":["netflix.tracing.zone0.RentMovie0"]},
{"name":"netflix.tracing.zone0.AccountLogin0","size":1000,"edges":["netflix.tracing.zone0.UserAccountInfo0"]},
{"name":"netflix.tracing.zone0.ComposePage0","size":1000,"edges":["netflix.tracing.zone0.ReadMovieInfo0"]},
{"name":"netflix.tracing.zone0.ReadMovieInfo0","size":1000,"edges":["netflix.tracing.zone0.memcached_movieInfo0","netflix.tracing.zone0.mongodb_movieInfo0","netflix.tracing.zone0.memcached_movieInfo1","netflix.tracing.zone0.mongodb_movieInfo1","netflix.tracing.zone0.memcached_movieInfo2","netflix.tracing.zone0.mongodb_movieInfo2","netflix.tracing.zone0.memcached_movieInfo3","netflix.tracing.zone0.mongodb_movieInfo3","netflix.tracing.zone0.memcached_movieInfo4","netflix.tracing.zone0.mongodb_movieInfo4","netflix.tracing.zone0.memcached_movieInfo5","netflix.tracing.zone0.mongodb_movieInfo5","netflix.tracing.zone0.memcached_movieInfo6","netflix.tracing.zone0.mongodb_movieInfo6","netflix.tracing.zone0.memcached_movieInfo7","netflix.tracing.zone0.mongodb_movieInfo7","netflix.tracing.zone0.memcached_movieInfo8","netflix.tracing.zone0.mongodb_movieInfo8","netflix.tracing.zone0.memcached_movieInfo9"]},
{"name":"netflix.tracing.zone0.UpdateMovieInfo0","size":1000,"edges":["netflix.tracing.zone0.memcached_movieInfo0","netflix.tracing.zone0.mongodb_movieInfo0","netflix.tracing.zone0.memcached_movieInfo1","netflix.tracing.zone0.mongodb_movieInfo1","netflix.tracing.zone0.memcached_movieInfo2","netflix.tracing.zone0.mongodb_movieInfo2","netflix.tracing.zone0.memcached_movieInfo3","netflix.tracing.zone0.mongodb_movieInfo3","netflix.tracing.zone0.memcached_movieInfo4","netflix.tracing.zone0.mongodb_movieInfo4","netflix.tracing.zone0.memcached_movieInfo5","netflix.tracing.zone0.mongodb_movieInfo5","netflix.tracing.zone0.memcached_movieInfo6","netflix.tracing.zone0.mongodb_movieInfo6","netflix.tracing.zone0.memcached_movieInfo7","netflix.tracing.zone0.mongodb_movieInfo7","netflix.tracing.zone0.memcached_movieInfo8","netflix.tracing.zone0.mongodb_movieInfo8","netflix.tracing.zone0.memcached_movieInfo9"]},
{"name":"netflix.tracing.zone0.MoviesNFS0","size":1000,"edges":["netflix.tracing.zone0.VideoPlayer0"]},
{"name":"netflix.tracing.zone0.ReviewStorage0","size":1000,"edges":["netflix.tracing.zone0.ReviewsNFS0"]},
{"name":"netflix.tracing.zone0.ReviewsNFS0","size":1000,"edges":["netflix.tracing.zone0.ReviewStorage0"]},
{"name":"netflix.tracing.zone0.MovieReviewDB0","size":1000,"edges":["netflix.tracing.zone0.memcached_movieReview0","netflix.tracing.zone0.mongodb_movieReview0","netflix.tracing.zone0.memcached_movieReview1","netflix.tracing.zone0.mongodb_movieReview1","netflix.tracing.zone0.memcached_movieReview2","netflix.tracing.zone0.mongodb_movieReview2","netflix.tracing.zone0.memcached_movieReview3","netflix.tracing.zone0.mongodb_movieReview3","netflix.tracing.zone0.memcached_movieReview4","netflix.tracing.zone0.mongodb_movieReview4","netflix.tracing.zone0.memcached_movieReview5","netflix.tracing.zone0.mongodb_movieReview5","netflix.tracing.zone0.memcached_movieReview6","netflix.tracing.zone0.mongodb_movieReview6","netflix.tracing.zone0.memcached_movieReview7","netflix.tracing.zone0.mongodb_movieReview7","netflix.tracing.zone0.memcached_movieReview8","netflix.tracing.zone0.mongodb_movieReview8","netflix.tracing.zone0.memcached_movieReview9"]},
{"name":"netflix.tracing.zone0.UserReviewDB0","size":1000,"edges":["netflix.tracing.zone0.memcached_userReview0","netflix.tracing.zone0.mongodb_userReview0","netflix.tracing.zone0.memcached_userReview1","netflix.tracing.zone0.mongodb_userReview1","netflix.tracing.zone0.memcached_userReview2","netflix.tracing.zone0.mongodb_userReview2","netflix.tracing.zone0.memcached_userReview3","netflix.tracing.zone0.mongodb_userReview3","netflix.tracing.zone0.memcached_userReview4","netflix.tracing.zone0.mongodb_userReview4","netflix.tracing.zone0.memcached_userReview5","netflix.tracing.zone0.mongodb_userReview5","netflix.tracing.zone0.memcached_userReview6","netflix.tracing.zone0.mongodb_userReview6","netflix.tracing.zone0.memcached_userReview7","netflix.tracing.zone0.mongodb_userReview7","netflix.tracing.zone0.memcached_userReview8","netflix.tracing.zone0.mongodb_userReview8","netflix.tracing.zone0.memcached_userReview9"]},
{"name":"netflix.tracing.zone0.memcached_castDB0","size":1000,"edges":["netflix.tracing.zone0.CastInfo0"]},
{"name":"netflix.tracing.zone0.mongodb_castDB0","size":1000,"edges":["netflix.tracing.zone0.CastInfo0"]},
{"name":"netflix.tracing.zone0.memcached_photosDB0","size":1000,"edges":["netflix.tracing.zone0.Photos0"]},
{"name":"netflix.tracing.zone0.mongodb_photosDB0","size":1000,"edges":["netflix.tracing.zone0.Photos0"]},
{"name":"netflix.tracing.zone0.memcached_videoPathDB0","size":1000,"edges":["netflix.tracing.zone0.Videos0"]},
{"name":"netflix.tracing.zone0.mongodb_videoPathDB0","size":1000,"edges":["netflix.tracing.zone0.Videos0"]},
{"name":"netflix.tracing.zone1.nginx0","size":1000,"edges":["netflix.tracing.zone1.php-fpm0"]},
{"name":"netflix.tracing.zone1.php-fpm0","size":1000,"edges":["netflix.tracing.zone1.ReviewText0","netflix.tracing.zone1.AssignRating0","netflix.tracing.zone1.UniqueID0","netflix.tracing.zone1.MovieID0","netflix.tracing.zone1.MoviePlot0","netflix.tracing.zone1.MovieThumbnail0","netflix.tracing.zone1.MovieRating0","netflix.tracing.zone1.CastInfo0","netflix.tracing.zone1.WatchNext0","netflix.tracing.zone1.MovieReviews0","netflix.tracing.zone1.Photos0","netflix.tracing.zone1.Videos0","netflix.tracing.zone1.xapian0","netflix.tracing.zone1.MovieRecommendations0","netflix.tracing.zone1.Ads0"]},
{"name":"netflix.tracing.zone1.ReviewText0","size":1000,"edges":["netflix.tracing.zone1.ComposeReview0"]},
{"name":"netflix.tracing.zone1.AssignRating0","size":1000,"edges":["netflix.tracing.zone1.ComposeReview0"]},
{"name":"netflix.tracing.zone1.MovieID0","size":1000,"edges":["netflix.tracing.zone1.ComposeReview0"]},
{"name":"netflix.tracing.zone1.UniqueID0","size":1000,"edges":["netflix.tracing.zone1.ComposeReview0"]},
{"name":"netflix.tracing.zone1.MoviePlot0","size":1000,"edges":["netflix.tracing.zone1.ComposePage0"]},
{"name":"netflix.tracing.zone1.MovieThumbnail0","size":1000,"edges":["netflix.tracing.zone1.ComposePage0"]},
{"name":"netflix.tracing.zone1.MovieRating0","size":1000,"edges":["netflix.tracing.zone1.ComposePage0"]},
{"name":"netflix.tracing.zone1.CastInfo0","size":1000,"edges":["netflix.tracing.zone1.ComposePage0","netflix.tracing.zone1.memcached_castDB0"]},
{"name":"netflix.tracing.zone1.WatchNext0","size":1000,"edges":["netflix.tracing.zone1.ComposePage0"]},
{"name":"netflix.tracing.zone1.MovieReviews0","size":1000,"edges":["netflix.tracing.zone1.ComposePage0"]},
{"name":"netflix.tracing.zone1.Photos0","size":1000,"edges":["netflix.tracing.zone1.ComposePage0","netflix.tracing.zone1.memcached_photosDB0"]},
{"name":"netflix.tracing.zone1.Videos0","size":1000,"edges":["netflix.tracing.zone1.ComposePage0","netflix.tracing.zone1.VideosNFS0","netflix.tracing.zone1.memcached_videoPathDB0"]},
{"name":"netflix.tracing.zone1.Favorite0","size":1000,"edges":["netflix.tracing.zone1.WatchList0"]},
{"name":"netflix.tracing.zone1.Ads0","size":1000,"edges":["netflix.tracing.zone1.UserAccountInfo0","netflix.tracing.zone1.AdsUtilityMatrix0"]},
{"name":"netflix.tracing.zone1.AdsUtilityMatrix0","size":1000,"edges":["netflix.tracing.zone1.Ads0"]},
{"name":"netflix.tracing.zone1.memcached_ads_recommendations0","size":1000,"edges":["netflix.tracing.zone1.Ads0"]},
{"name":"netflix.tracing.zone1.WatchList0","size":1000,"edges":["netflix.tracing.zone1.Favorite0"]},
{"name":"netflix.tracing.zone1.MovieRecommendations0","size":1000,"edges":["netflix.tracing.zone1.MovieUtilityMatrix0"]},
{"name":"netflix.tracing.zone1.memcached_movies_recommendations0","size":1000,"edges":["netflix.tracing.zone1.MovieRecommendations0"]},
{"name":"netflix.tracing.zone1.xapian0","size":1000,"edges":["netflix.tracing.zone1.php-fpm0"]},
{"name":"netflix.tracing.zone1.MovieUtilityMatrix0","size":1000,"edges":["netflix.tracing.zone1.MovieRecommendations0"]},
{"name":"netflix.tracing.zone1.UserAccountInfo0","size":1000,"edges":["netflix.tracing.zone1.AccountLogin0"]},
{"name":"netflix.tracing.zone1.FavoriteStorage0","size":1000,"edges":["netflix.tracing.zone1.memcached_favorite0"]},
{"name":"netflix.tracing.zone1.memcached_favorite0","size":1000,"edges":["netflix.tracing.zone1.FavoriteStorage0"]},
{"name":"netflix.tracing.zone1.mongodb_favorite0","size":1000,"edges":["netflix.tracing.zone1.FavoriteStorage0"]},
{"name":"netflix.tracing.zone1.VideosNFS0","size":1000,"edges":["netflix.tracing.zone1.Videos0"]},
{"name":"netflix.tracing.zone1.RentMovie0","size":1000,"edges":["netflix.tracing.zone1.Payment0"]},
{"name":"netflix.tracing.zone1.VideoPlayer0","size":1000,"edges":["netflix.tracing.zone1.MoviesNFS0","netflix.tracing.zone1.memcached_movieDB0","netflix.tracing.zone1.mongodb_movieDB0","netflix.tracing.zone1.memcached_movieDB1","netflix.tracing.zone1.mongodb_movieDB1","netflix.tracing.zone1.memcached_movieDB2","netflix.tracing.zone1.mongodb_movieDB2","netflix.tracing.zone1.memcached_movieDB3","netflix.tracing.zone1.mongodb_movieDB3","netflix.tracing.zone1.memcached_movieDB4","netflix.tracing.zone1.mongodb_movieDB4","netflix.tracing.zone1.memcached_movieDB5","netflix.tracing.zone1.mongodb_movieDB5","netflix.tracing.zone1.memcached_movieDB6","netflix.tracing.zone1.mongodb_movieDB6","netflix.tracing.zone1.memcached_movieDB7","netflix.tracing.zone1.mongodb_movieDB7","netflix.tracing.zone1.memcached_movieDB8","netflix.tracing.zone1.mongodb_movieDB8","netflix.tracing.zone1.memcached_movieDB9"]},
{"name":"netflix.tracing.zone1.ComposeReview0","size":1000,"edges":["netflix.tracing.zone1.AccountLogin0","netflix.tracing.zone1.UserReviewDB0","netflix.tracing.zone1.MovieReviewDB0","netflix.tracing.zone1.ReviewStorage0"]},
{"name":"netflix.tracing.zone1.Payment0","size":1000,"edges":["netflix.tracing.zone1.RentMovie0"]},
{"name":"netflix.tracing.zone1.AccountLogin0","size":1000,"edges":["netflix.tracing.zone1.UserAccountInfo0"]},
{"name":"netflix.tracing.zone1.ComposePage0","size":1000,"edges":["netflix.tracing.zone1.ReadMovieInfo0"]},
{"name":"netflix.tracing.zone1.ReadMovieInfo0","size":1000,"edges":["netflix.tracing.zone1.memcached_movieInfo0","netflix.tracing.zone1.mongodb_movieInfo0","netflix.tracing.zone1.memcached_movieInfo1","netflix.tracing.zone1.mongodb_movieInfo1","netflix.tracing.zone1.memcached_movieInfo2","netflix.tracing.zone1.mongodb_movieInfo2","netflix.tracing.zone1.memcached_movieInfo3","netflix.tracing.zone1.mongodb_movieInfo3","netflix.tracing.zone1.memcached_movieInfo4","netflix.tracing.zone1.mongodb_movieInfo4","netflix.tracing.zone1.memcached_movieInfo5","netflix.tracing.zone1.mongodb_movieInfo5","netflix.tracing.zone1.memcached_movieInfo6","netflix.tracing.zone1.mongodb_movieInfo6","netflix.tracing.zone1.memcached_movieInfo7","netflix.tracing.zone1.mongodb_movieInfo7","netflix.tracing.zone1.memcached_movieInfo8","netflix.tracing.zone1.mongodb_movieInfo8","netflix.tracing.zone1.memcached_movieInfo9"]},
{"name":"netflix.tracing.zone1.UpdateMovieInfo0","size":1000,"edges":["netflix.tracing.zone1.memcached_movieInfo0","netflix.tracing.zone1.mongodb_movieInfo0","netflix.tracing.zone1.memcached_movieInfo1","netflix.tracing.zone1.mongodb_movieInfo1","netflix.tracing.zone1.memcached_movieInfo2","netflix.tracing.zone1.mongodb_movieInfo2","netflix.tracing.zone1.memcached_movieInfo3","netflix.tracing.zone1.mongodb_movieInfo3","netflix.tracing.zone1.memcached_movieInfo4","netflix.tracing.zone1.mongodb_movieInfo4","netflix.tracing.zone1.memcached_movieInfo5","netflix.tracing.zone1.mongodb_movieInfo5","netflix.tracing.zone1.memcached_movieInfo6","netflix.tracing.zone1.mongodb_movieInfo6","netflix.tracing.zone1.memcached_movieInfo7","netflix.tracing.zone1.mongodb_movieInfo7","netflix.tracing.zone1.memcached_movieInfo8","netflix.tracing.zone1.mongodb_movieInfo8","netflix.tracing.zone1.memcached_movieInfo9"]},
{"name":"netflix.tracing.zone1.MoviesNFS0","size":1000,"edges":["netflix.tracing.zone1.VideoPlayer0"]},
{"name":"netflix.tracing.zone1.ReviewStorage0","size":1000,"edges":["netflix.tracing.zone1.ReviewsNFS0"]},
{"name":"netflix.tracing.zone1.ReviewsNFS0","size":1000,"edges":["netflix.tracing.zone1.ReviewStorage0"]},
{"name":"netflix.tracing.zone1.MovieReviewDB0","size":1000,"edges":["netflix.tracing.zone1.memcached_movieReview0","netflix.tracing.zone1.mongodb_movieReview0","netflix.tracing.zone1.memcached_movieReview1","netflix.tracing.zone1.mongodb_movieReview1","netflix.tracing.zone1.memcached_movieReview2","netflix.tracing.zone1.mongodb_movieReview2","netflix.tracing.zone1.memcached_movieReview3","netflix.tracing.zone1.mongodb_movieReview3","netflix.tracing.zone1.memcached_movieReview4","netflix.tracing.zone1.mongodb_movieReview4","netflix.tracing.zone1.memcached_movieReview5","netflix.tracing.zone1.mongodb_movieReview5","netflix.tracing.zone1.memcached_movieReview6","netflix.tracing.zone1.mongodb_movieReview6","netflix.tracing.zone1.memcached_movieReview7","netflix.tracing.zone1.mongodb_movieReview7","netflix.tracing.zone1.memcached_movieReview8","netflix.tracing.zone1.mongodb_movieReview8","netflix.tracing.zone1.memcached_movieReview9"]},
{"name":"netflix.tracing.zone1.UserReviewDB0","size":1000,"edges":["netflix.tracing.zone1.memcached_userReview0","netflix.tracing.zone1.mongodb_userReview0","netflix.tracing.zone1.memcached_userReview1","netflix.tracing.zone1.mongodb_userReview1","netflix.tracing.zone1.memcached_userReview2","netflix.tracing.zone1.mongodb_userReview2","netflix.tracing.zone1.memcached_userReview3","netflix.tracing.zone1.mongodb_userReview3","netflix.tracing.zone1.memcached_userReview4","netflix.tracing.zone1.mongodb_userReview4","netflix.tracing.zone1.memcached_userReview5","netflix.tracing.zone1.mongodb_userReview5","netflix.tracing.zone1.memcached_userReview6","netflix.tracing.zone1.mongodb_userReview6","netflix.tracing.zone1.memcached_userReview7","netflix.tracing.zone1.mongodb_userReview7","netflix.tracing.zone1.memcached_userReview8","netflix.tracing.zone1.mongodb_userReview8","netflix.tracing.zone1.memcached_userReview9"]},
{"name":"netflix.tracing.zone1.memcached_castDB0","size":1000,"edges":["netflix.tracing.zone1.CastInfo0"]},
{"name":"netflix.tracing.zone1.mongodb_castDB0","size":1000,"edges":["netflix.tracing.zone1.CastInfo0"]},
{"name":"netflix.tracing.zone1.memcached_photosDB0","size":1000,"edges":["netflix.tracing.zone1.Photos0"]},
{"name":"netflix.tracing.zone1.mongodb_photosDB0","size":1000,"edges":["netflix.tracing.zone1.Photos0"]},
{"name":"netflix.tracing.zone1.memcached_videoPathDB0","size":1000,"edges":["netflix.tracing.zone1.Videos0"]},
{"name":"netflix.tracing.zone1.mongodb_videoPathDB0","size":1000,"edges":["netflix.tracing.zone1.Videos0"]},
{"name":"netflix.tracing.zone2.nginx0","size":1000,"edges":["netflix.tracing.zone2.php-fpm0"]},
{"name":"netflix.tracing.zone2.php-fpm0","size":1000,"edges":["netflix.tracing.zone2.ReviewText0","netflix.tracing.zone2.AssignRating0","netflix.tracing.zone2.UniqueID0","netflix.tracing.zone2.MovieID0","netflix.tracing.zone2.MoviePlot0","netflix.tracing.zone2.MovieThumbnail0","netflix.tracing.zone2.MovieRating0","netflix.tracing.zone2.CastInfo0","netflix.tracing.zone2.WatchNext0","netflix.tracing.zone2.MovieReviews0","netflix.tracing.zone2.Photos0","netflix.tracing.zone2.Videos0","netflix.tracing.zone2.xapian0","netflix.tracing.zone2.MovieRecommendations0","netflix.tracing.zone2.Ads0"]},
{"name":"netflix.tracing.zone2.ReviewText0","size":1000,"edges":["netflix.tracing.zone2.ComposeReview0"]},
{"name":"netflix.tracing.zone2.AssignRating0","size":1000,"edges":["netflix.tracing.zone2.ComposeReview0"]},
{"name":"netflix.tracing.zone2.MovieID0","size":1000,"edges":["netflix.tracing.zone2.ComposeReview0"]},
{"name":"netflix.tracing.zone2.UniqueID0","size":1000,"edges":["netflix.tracing.zone2.ComposeReview0"]},
{"name":"netflix.tracing.zone2.MoviePlot0","size":1000,"edges":["netflix.tracing.zone2.ComposePage0"]},
{"name":"netflix.tracing.zone2.MovieThumbnail0","size":1000,"edges":["netflix.tracing.zone2.ComposePage0"]},
{"name":"netflix.tracing.zone2.MovieRating0","size":1000,"edges":["netflix.tracing.zone2.ComposePage0"]},
{"name":"netflix.tracing.zone2.CastInfo0","size":1000,"edges":["netflix.tracing.zone2.ComposePage0","netflix.tracing.zone2.memcached_castDB0"]},
{"name":"netflix.tracing.zone2.WatchNext0","size":1000,"edges":["netflix.tracing.zone2.ComposePage0"]},
{"name":"netflix.tracing.zone2.MovieReviews0","size":1000,"edges":["netflix.tracing.zone2.ComposePage0"]},
{"name":"netflix.tracing.zone2.Photos0","size":1000,"edges":["netflix.tracing.zone2.ComposePage0","netflix.tracing.zone2.memcached_photosDB0"]},
{"name":"netflix.tracing.zone2.Videos0","size":1000,"edges":["netflix.tracing.zone2.ComposePage0","netflix.tracing.zone2.VideosNFS0","netflix.tracing.zone2.memcached_videoPathDB0"]},
{"name":"netflix.tracing.zone2.Favorite0","size":1000,"edges":["netflix.tracing.zone2.WatchList0"]},
{"name":"netflix.tracing.zone2.Ads0","size":1000,"edges":["netflix.tracing.zone2.UserAccountInfo0","netflix.tracing.zone2.AdsUtilityMatrix0"]},
{"name":"netflix.tracing.zone2.AdsUtilityMatrix0","size":1000,"edges":["netflix.tracing.zone2.Ads0"]},
{"name":"netflix.tracing.zone2.memcached_ads_recommendations0","size":1000,"edges":["netflix.tracing.zone2.Ads0"]},
{"name":"netflix.tracing.zone2.WatchList0","size":1000,"edges":["netflix.tracing.zone2.Favorite0"]},
{"name":"netflix.tracing.zone2.MovieRecommendations0","size":1000,"edges":["netflix.tracing.zone2.MovieUtilityMatrix0"]},
{"name":"netflix.tracing.zone2.memcached_movies_recommendations0","size":1000,"edges":["netflix.tracing.zone2.MovieRecommendations0"]},
{"name":"netflix.tracing.zone2.xapian0","size":1000,"edges":["netflix.tracing.zone2.php-fpm0"]},
{"name":"netflix.tracing.zone2.MovieUtilityMatrix0","size":1000,"edges":["netflix.tracing.zone2.MovieRecommendations0"]},
{"name":"netflix.tracing.zone2.UserAccountInfo0","size":1000,"edges":["netflix.tracing.zone2.AccountLogin0"]},
{"name":"netflix.tracing.zone2.FavoriteStorage0","size":1000,"edges":["netflix.tracing.zone2.memcached_favorite0"]},
{"name":"netflix.tracing.zone2.memcached_favorite0","size":1000,"edges":["netflix.tracing.zone2.FavoriteStorage0"]},
{"name":"netflix.tracing.zone2.mongodb_favorite0","size":1000,"edges":["netflix.tracing.zone2.FavoriteStorage0"]},
{"name":"netflix.tracing.zone2.VideosNFS0","size":1000,"edges":["netflix.tracing.zone2.Videos0"]},
{"name":"netflix.tracing.zone2.RentMovie0","size":1000,"edges":["netflix.tracing.zone2.Payment0"]},
{"name":"netflix.tracing.zone2.VideoPlayer0","size":1000,"edges":["netflix.tracing.zone2.MoviesNFS0","netflix.tracing.zone2.memcached_movieDB0","netflix.tracing.zone2.mongodb_movieDB0","netflix.tracing.zone2.memcached_movieDB1","netflix.tracing.zone2.mongodb_movieDB1","netflix.tracing.zone2.memcached_movieDB2","netflix.tracing.zone2.mongodb_movieDB2","netflix.tracing.zone2.memcached_movieDB3","netflix.tracing.zone2.mongodb_movieDB3","netflix.tracing.zone2.memcached_movieDB4","netflix.tracing.zone2.mongodb_movieDB4","netflix.tracing.zone2.memcached_movieDB5","netflix.tracing.zone2.mongodb_movieDB5","netflix.tracing.zone2.memcached_movieDB6","netflix.tracing.zone2.mongodb_movieDB6","netflix.tracing.zone2.memcached_movieDB7","netflix.tracing.zone2.mongodb_movieDB7","netflix.tracing.zone2.memcached_movieDB8","netflix.tracing.zone2.mongodb_movieDB8","netflix.tracing.zone2.memcached_movieDB9"]},
{"name":"netflix.tracing.zone2.ComposeReview0","size":1000,"edges":["netflix.tracing.zone2.AccountLogin0","netflix.tracing.zone2.UserReviewDB0","netflix.tracing.zone2.MovieReviewDB0","netflix.tracing.zone2.ReviewStorage0"]},
{"name":"netflix.tracing.zone2.Payment0","size":1000,"edges":["netflix.tracing.zone2.RentMovie0"]},
{"name":"netflix.tracing.zone2.AccountLogin0","size":1000,"edges":["netflix.tracing.zone2.UserAccountInfo0"]},
{"name":"netflix.tracing.zone2.ComposePage0","size":1000,"edges":["netflix.tracing.zone2.ReadMovieInfo0"]},
{"name":"netflix.tracing.zone2.ReadMovieInfo0","size":1000,"edges":["netflix.tracing.zone2.memcached_movieInfo0","netflix.tracing.zone2.mongodb_movieInfo0","netflix.tracing.zone2.memcached_movieInfo1","netflix.tracing.zone2.mongodb_movieInfo1","netflix.tracing.zone2.memcached_movieInfo2","netflix.tracing.zone2.mongodb_movieInfo2","netflix.tracing.zone2.memcached_movieInfo3","netflix.tracing.zone2.mongodb_movieInfo3","netflix.tracing.zone2.memcached_movieInfo4","netflix.tracing.zone2.mongodb_movieInfo4","netflix.tracing.zone2.memcached_movieInfo5","netflix.tracing.zone2.mongodb_movieInfo5","netflix.tracing.zone2.memcached_movieInfo6","netflix.tracing.zone2.mongodb_movieInfo6","netflix.tracing.zone2.memcached_movieInfo7","netflix.tracing.zone2.mongodb_movieInfo7","netflix.tracing.zone2.memcached_movieInfo8","netflix.tracing.zone2.mongodb_movieInfo8","netflix.tracing.zone2.memcached_movieInfo9"]},
{"name":"netflix.tracing.zone2.UpdateMovieInfo0","size":1000,"edges":["netflix.tracing.zone2.memcached_movieInfo0","netflix.tracing.zone2.mongodb_movieInfo0","netflix.tracing.zone2.memcached_movieInfo1","netflix.tracing.zone2.mongodb_movieInfo1","netflix.tracing.zone2.memcached_movieInfo2","netflix.tracing.zone2.mongodb_movieInfo2","netflix.tracing.zone2.memcached_movieInfo3","netflix.tracing.zone2.mongodb_movieInfo3","netflix.tracing.zone2.memcached_movieInfo4","netflix.tracing.zone2.mongodb_movieInfo4","netflix.tracing.zone2.memcached_movieInfo5","netflix.tracing.zone2.mongodb_movieInfo5","netflix.tracing.zone2.memcached_movieInfo6","netflix.tracing.zone2.mongodb_movieInfo6","netflix.tracing.zone2.memcached_movieInfo7","netflix.tracing.zone2.mongodb_movieInfo7","netflix.tracing.zone2.memcached_movieInfo8","netflix.tracing.zone2.mongodb_movieInfo8","netflix.tracing.zone2.memcached_movieInfo9"]},
{"name":"netflix.tracing.zone2.MoviesNFS0","size":1000,"edges":["netflix.tracing.zone2.VideoPlayer0"]},
{"name":"netflix.tracing.zone2.ReviewStorage0","size":1000,"edges":["netflix.tracing.zone2.ReviewsNFS0"]},
{"name":"netflix.tracing.zone2.ReviewsNFS0","size":1000,"edges":["netflix.tracing.zone2.ReviewStorage0"]},
{"name":"netflix.tracing.zone2.MovieReviewDB0","size":1000,"edges":["netflix.tracing.zone2.memcached_movieReview0","netflix.tracing.zone2.mongodb_movieReview0","netflix.tracing.zone2.memcached_movieReview1","netflix.tracing.zone2.mongodb_movieReview1","netflix.tracing.zone2.memcached_movieReview2","netflix.tracing.zone2.mongodb_movieReview2","netflix.tracing.zone2.memcached_movieReview3","netflix.tracing.zone2.mongodb_movieReview3","netflix.tracing.zone2.memcached_movieReview4","netflix.tracing.zone2.mongodb_movieReview4","netflix.tracing.zone2.memcached_movieReview5","netflix.tracing.zone2.mongodb_movieReview5","netflix.tracing.zone2.memcached_movieReview6","netflix.tracing.zone2.mongodb_movieReview6","netflix.tracing.zone2.memcached_movieReview7","netflix.tracing.zone2.mongodb_movieReview7","netflix.tracing.zone2.memcached_movieReview8","netflix.tracing.zone2.mongodb_movieReview8","netflix.tracing.zone2.memcached_movieReview9"]},
{"name":"netflix.tracing.zone2.UserReviewDB0","size":1000,"edges":["netflix.tracing.zone2.memcached_userReview0","netflix.tracing.zone2.mongodb_userReview0","netflix.tracing.zone2.memcached_userReview1","netflix.tracing.zone2.mongodb_userReview1","netflix.tracing.zone2.memcached_userReview2","netflix.tracing.zone2.mongodb_userReview2","netflix.tracing.zone2.memcached_userReview3","netflix.tracing.zone2.mongodb_userReview3","netflix.tracing.zone2.memcached_userReview4","netflix.tracing.zone2.mongodb_userReview4","netflix.tracing.zone2.memcached_userReview5","netflix.tracing.zone2.mongodb_userReview5","netflix.tracing.zone2.memcached_userReview6","netflix.tracing.zone2.mongodb_userReview6","netflix.tracing.zone2.memcached_userReview7","netflix.tracing.zone2.mongodb_userReview7","netflix.tracing.zone2.memcached_userReview8","netflix.tracing.zone2.mongodb_userReview8","netflix.tracing.zone2.memcached_userReview9"]},
{"name":"netflix.tracing.zone2.memcached_castDB0","size":1000,"edges":["netflix.tracing.zone2.CastInfo0"]},
{"name":"netflix.tracing.zone2.mongodb_castDB0","size":1000,"edges":["netflix.tracing.zone2.CastInfo0"]},
{"name":"netflix.tracing.zone2.memcached_photosDB0","size":1000,"edges":["netflix.tracing.zone2.Photos0"]},
{"name":"netflix.tracing.zone2.mongodb_photosDB0","size":1000,"edges":["netflix.tracing.zone2.Photos0"]},
{"name":"netflix.tracing.zone2.memcached_videoPathDB0","size":1000,"edges":["netflix.tracing.zone2.Videos0"]},
{"name":"netflix.tracing.zone2.mongodb_videoPathDB0","size":1000,"edges":["netflix.tracing.zone2.Videos0"]},
{"name":"netflix.tracing.zone0.memcached_movieInfo0","size":1000,"edges":["netflix.tracing.zone0.UpdateMovieInfo0"]},
{"name":"netflix.tracing.zone0.mongodb_movieInfo0","size":1000,"edges":["netflix.tracing.zone0.UpdateMovieInfo0"]},
{"name":"netflix.tracing.zone0.memcached_movieDB0","size":1000,"edges":["netflix.tracing.zone0.VideoPlayer0"]},
{"name":"netflix.tracing.zone0.mongodb_movieDB0","size":1000,"edges":["netflix.tracing.zone0.VideoPlayer0"]},
{"name":"netflix.tracing.zone0.memcached_movieReview0","size":1000,"edges":["netflix.tracing.zone0.MovieReviewDB0"]},
{"name":"netflix.tracing.zone0.mongodb_movieReview0","size":1000,"edges":["netflix.tracing.zone0.MovieReviewDB0"]},
{"name":"netflix.tracing.zone0.memcached_userReview0","size":1000,"edges":["netflix.tracing.zone0.UserReviewDB0"]},
{"name":"netflix.tracing.zone0.mongodb_userReview0","size":1000,"edges":["netflix.tracing.zone0.UserReviewDB0"]},
{"name":"netflix.tracing.zone0.memcached_movieInfo1","size":1000,"edges":["netflix.tracing.zone0.UpdateMovieInfo0"]},
{"name":"netflix.tracing.zone0.mongodb_movieInfo1","size":1000,"edges":["netflix.tracing.zone0.UpdateMovieInfo0"]},
{"name":"netflix.tracing.zone0.memcached_movieDB1","size":1000,"edges":["netflix.tracing.zone0.VideoPlayer0"]},
{"name":"netflix.tracing.zone0.mongodb_movieDB1","size":1000,"edges":["netflix.tracing.zone0.VideoPlayer0"]},
{"name":"netflix.tracing.zone0.memcached_movieReview1","size":1000,"edges":["netflix.tracing.zone0.MovieReviewDB0"]},
{"name":"netflix.tracing.zone0.mongodb_movieReview1","size":1000,"edges":["netflix.tracing.zone0.MovieReviewDB0"]},
{"name":"netflix.tracing.zone0.memcached_userReview1","size":1000,"edges":["netflix.tracing.zone0.UserReviewDB0"]},
{"name":"netflix.tracing.zone0.mongodb_userReview1","size":1000,"edges":["netflix.tracing.zone0.UserReviewDB0"]},
{"name":"netflix.tracing.zone0.memcached_movieInfo2","size":1000,"edges":["netflix.tracing.zone0.UpdateMovieInfo0"]},
{"name":"netflix.tracing.zone0.mongodb_movieInfo2","size":1000,"edges":["netflix.tracing.zone0.UpdateMovieInfo0"]},
{"name":"netflix.tracing.zone0.memcached_movieDB2","size":1000,"edges":["netflix.tracing.zone0.VideoPlayer0"]},
{"name":"netflix.tracing.zone0.mongodb_movieDB2","size":1000,"edges":["netflix.tracing.zone0.VideoPlayer0"]},
{"name":"netflix.tracing.zone0.memcached_movieReview2","size":1000,"edges":["netflix.tracing.zone0.MovieReviewDB0"]},
{"name":"netflix.tracing.zone0.mongodb_movieReview2","size":1000,"edges":["netflix.tracing.zone0.MovieReviewDB0"]},
{"name":"netflix.tracing.zone0.memcached_userReview2","size":1000,"edges":["netflix.tracing.zone0.UserReviewDB0"]},
{"name":"netflix.tracing.zone0.mongodb_userReview2","size":1000,"edges":["netflix.tracing.zone0.UserReviewDB0"]},
{"name":"netflix.tracing.zone0.memcached_movieInfo3","size":1000,"edges":["netflix.tracing.zone0.UpdateMovieInfo0"]},
{"name":"netflix.tracing.zone0.mongodb_movieInfo3","size":1000,"edges":["netflix.tracing.zone0.UpdateMovieInfo0"]},
{"name":"netflix.tracing.zone0.memcached_movieDB3","size":1000,"edges":["netflix.tracing.zone0.VideoPlayer0"]},
{"name":"netflix.tracing.zone0.mongodb_movieDB3","size":1000,"edges":["netflix.tracing.zone0.VideoPlayer0"]},
{"name":"netflix.tracing.zone0.memcached_movieReview3","size":1000,"edges":["netflix.tracing.zone0.MovieReviewDB0"]},
{"name":"netflix.tracing.zone0.mongodb_movieReview3","size":1000,"edges":["netflix.tracing.zone0.MovieReviewDB0"]},
{"name":"netflix.tracing.zone0.memcached_userReview3","size":1000,"edges":["netflix.tracing.zone0.UserReviewDB0"]},
{"name":"netflix.tracing.zone0.mongodb_userReview3","size":1000,"edges":["netflix.tracing.zone0.UserReviewDB0"]},
{"name":"netflix.tracing.zone0.memcached_movieInfo4","size":1000,"edges":["netflix.tracing.zone0.UpdateMovieInfo0"]},
{"name":"netflix.tracing.zone0.mongodb_movieInfo4","size":1000,"edges":["netflix.tracing.zone0.UpdateMovieInfo0"]},
{"name":"netflix.tracing.zone0.memcached_movieDB4","size":1000,"edges":["netflix.tracing.zone0.VideoPlayer0"]},
{"name":"netflix.tracing.zone0.mongodb_movieDB4","size":1000,"edges":["netflix.tracing.zone0.VideoPlayer0"]},
{"name":"netflix.tracing.zone0.memcached_movieReview4","size":1000,"edges":["netflix.tracing.zone0.MovieReviewDB0"]},
{"name":"netflix.tracing.zone0.mongodb_movieReview4","size":1000,"edges":["netflix.tracing.zone0.MovieReviewDB0"]},
{"name":"netflix.tracing.zone0.memcached_userReview4","size":1000,"edges":["netflix.tracing.zone0.UserReviewDB0"]},
{"name":"netflix.tracing.zone0.mongodb_userReview4","size":1000,"edges":["netflix.tracing.zone0.UserReviewDB0"]},
{"name":"netflix.tracing.zone0.memcached_movieInfo5","size":1000,"edges":["netflix.tracing.zone0.UpdateMovieInfo0"]},
{"name":"netflix.tracing.zone0.mongodb_movieInfo5","size":1000,"edges":["netflix.tracing.zone0.UpdateMovieInfo0"]},
{"name":"netflix.tracing.zone0.memcached_movieDB5","size":1000,"edges":["netflix.tracing.zone0.VideoPlayer0"]},
{"name":"netflix.tracing.zone0.mongodb_movieDB5","size":1000,"edges":["netflix.tracing.zone0.VideoPlayer0"]},
{"name":"netflix.tracing.zone0.memcached_movieReview5","size":1000,"edges":["netflix.tracing.zone0.MovieReviewDB0"]},
{"name":"netflix.tracing.zone0.mongodb_movieReview5","size":1000,"edges":["netflix.tracing.zone0.MovieReviewDB0"]},
{"name":"netflix.tracing.zone0.memcached_userReview5","size":1000,"edges":["netflix.tracing.zone0.UserReviewDB0"]},
{"name":"netflix.tracing.zone0.mongodb_userReview5","size":1000,"edges":["netflix.tracing.zone0.UserReviewDB0"]},
{"name":"netflix.tracing.zone0.memcached_movieInfo6","size":1000,"edges":["netflix.tracing.zone0.UpdateMovieInfo0"]},
{"name":"netflix.tracing.zone0.mongodb_movieInfo6","size":1000,"edges":["netflix.tracing.zone0.UpdateMovieInfo0"]},
{"name":"netflix.tracing.zone0.memcached_movieDB6","size":1000,"edges":["netflix.tracing.zone0.VideoPlayer0"]},
{"name":"netflix.tracing.zone0.mongodb_movieDB6","size":1000,"edges":["netflix.tracing.zone0.VideoPlayer0"]},
{"name":"netflix.tracing.zone0.memcached_movieReview6","size":1000,"edges":["netflix.tracing.zone0.MovieReviewDB0"]},
{"name":"netflix.tracing.zone0.mongodb_movieReview6","size":1000,"edges":["netflix.tracing.zone0.MovieReviewDB0"]},
{"name":"netflix.tracing.zone0.memcached_userReview6","size":1000,"edges":["netflix.tracing.zone0.UserReviewDB0"]},
{"name":"netflix.tracing.zone0.mongodb_userReview6","size":1000,"edges":["netflix.tracing.zone0.UserReviewDB0"]},
{"name":"netflix.tracing.zone0.memcached_movieInfo7","size":1000,"edges":["netflix.tracing.zone0.UpdateMovieInfo0"]},
{"name":"netflix.tracing.zone0.mongodb_movieInfo7","size":1000,"edges":["netflix.tracing.zone0.UpdateMovieInfo0"]},
{"name":"netflix.tracing.zone0.memcached_movieDB7","size":1000,"edges":["netflix.tracing.zone0.VideoPlayer0"]},
{"name":"netflix.tracing.zone0.mongodb_movieDB7","size":1000,"edges":["netflix.tracing.zone0.VideoPlayer0"]},
{"name":"netflix.tracing.zone0.memcached_movieReview7","size":1000,"edges":["netflix.tracing.zone0.MovieReviewDB0"]},
{"name":"netflix.tracing.zone0.mongodb_movieReview7","size":1000,"edges":["netflix.tracing.zone0.MovieReviewDB0"]},
{"name":"netflix.tracing.zone0.memcached_userReview7","size":1000,"edges":["netflix.tracing.zone0.UserReviewDB0"]},
{"name":"netflix.tracing.zone0.mongodb_userReview7","size":1000,"edges":["netflix.tracing.zone0.UserReviewDB0"]},
{"name":"netflix.tracing.zone0.memcached_movieInfo8","size":1000,"edges":["netflix.tracing.zone0.UpdateMovieInfo0"]},
{"name":"netflix.tracing.zone0.mongodb_movieInfo8","size":1000,"edges":["netflix.tracing.zone0.UpdateMovieInfo0"]},
{"name":"netflix.tracing.zone0.memcached_movieDB8","size":1000,"edges":["netflix.tracing.zone0.VideoPlayer0"]},
{"name":"netflix.tracing.zone0.mongodb_movieDB8","size":1000,"edges":["netflix.tracing.zone0.VideoPlayer0"]},
{"name":"netflix.tracing.zone0.memcached_movieReview8","size":1000,"edges":["netflix.tracing.zone0.MovieReviewDB0"]},
{"name":"netflix.tracing.zone0.mongodb_movieReview8","size":1000,"edges":["netflix.tracing.zone0.MovieReviewDB0"]},
{"name":"netflix.tracing.zone0.memcached_userReview8","size":1000,"edges":["netflix.tracing.zone0.UserReviewDB0"]},
{"name":"netflix.tracing.zone0.mongodb_userReview8","size":1000,"edges":["netflix.tracing.zone0.UserReviewDB0"]},
{"name":"netflix.tracing.zone0.memcached_movieInfo9","size":1000,"edges":["netflix.tracing.zone0.UpdateMovieInfo0"]},
{"name":"netflix.tracing.zone0.mongodb_movieInfo9","size":1000,"edges":["netflix.tracing.zone0.UpdateMovieInfo0"]},
{"name":"netflix.tracing.zone0.memcached_movieDB9","size":1000,"edges":["netflix.tracing.zone0.VideoPlayer0"]},
{"name":"netflix.tracing.zone0.mongodb_movieDB9","size":1000,"edges":["netflix.tracing.zone0.VideoPlayer0"]},
{"name":"netflix.tracing.zone0.memcached_movieReview9","size":1000,"edges":["netflix.tracing.zone0.MovieReviewDB0"]},
{"name":"netflix.tracing.zone0.mongodb_movieReview9","size":1000,"edges":["netflix.tracing.zone0.MovieReviewDB0"]},
{"name":"netflix.tracing.zone0.memcached_userReview9","size":1000,"edges":["netflix.tracing.zone0.UserReviewDB0"]},
{"name":"netflix.tracing.zone0.mongodb_userReview9","size":1000,"edges":["netflix.tracing.zone0.UserReviewDB0"]},
{"name":"netflix.tracing.zone1.memcached_movieInfo0","size":1000,"edges":["netflix.tracing.zone1.UpdateMovieInfo0"]},
{"name":"netflix.tracing.zone1.mongodb_movieInfo0","size":1000,"edges":["netflix.tracing.zone1.UpdateMovieInfo0"]},
{"name":"netflix.tracing.zone1.memcached_movieDB0","size":1000,"edges":["netflix.tracing.zone1.VideoPlayer0"]},
{"name":"netflix.tracing.zone1.mongodb_movieDB0","size":1000,"edges":["netflix.tracing.zone1.VideoPlayer0"]},
{"name":"netflix.tracing.zone1.memcached_movieReview0","size":1000,"edges":["netflix.tracing.zone1.MovieReviewDB0"]},
{"name":"netflix.tracing.zone1.mongodb_movieReview0","size":1000,"edges":["netflix.tracing.zone1.MovieReviewDB0"]},
{"name":"netflix.tracing.zone1.memcached_userReview0","size":1000,"edges":["netflix.tracing.zone1.UserReviewDB0"]},
{"name":"netflix.tracing.zone1.mongodb_userReview0","size":1000,"edges":["netflix.tracing.zone1.UserReviewDB0"]},
{"name":"netflix.tracing.zone1.memcached_movieInfo1","size":1000,"edges":["netflix.tracing.zone1.UpdateMovieInfo0"]},
{"name":"netflix.tracing.zone1.mongodb_movieInfo1","size":1000,"edges":["netflix.tracing.zone1.UpdateMovieInfo0"]},
{"name":"netflix.tracing.zone1.memcached_movieDB1","size":1000,"edges":["netflix.tracing.zone1.VideoPlayer0"]},
{"name":"netflix.tracing.zone1.mongodb_movieDB1","size":1000,"edges":["netflix.tracing.zone1.VideoPlayer0"]},
{"name":"netflix.tracing.zone1.memcached_movieReview1","size":1000,"edges":["netflix.tracing.zone1.MovieReviewDB0"]},
{"name":"netflix.tracing.zone1.mongodb_movieReview1","size":1000,"edges":["netflix.tracing.zone1.MovieReviewDB0"]},
{"name":"netflix.tracing.zone1.memcached_userReview1","size":1000,"edges":["netflix.tracing.zone1.UserReviewDB0"]},
{"name":"netflix.tracing.zone1.mongodb_userReview1","size":1000,"edges":["netflix.tracing.zone1.UserReviewDB0"]},
{"name":"netflix.tracing.zone1.memcached_movieInfo2","size":1000,"edges":["netflix.tracing.zone1.UpdateMovieInfo0"]},
{"name":"netflix.tracing.zone1.mongodb_movieInfo2","size":1000,"edges":["netflix.tracing.zone1.UpdateMovieInfo0"]},
{"name":"netflix.tracing.zone1.memcached_movieDB2","size":1000,"edges":["netflix.tracing.zone1.VideoPlayer0"]},
{"name":"netflix.tracing.zone1.mongodb_movieDB2","size":1000,"edges":["netflix.tracing.zone1.VideoPlayer0"]},
{"name":"netflix.tracing.zone1.memcached_movieReview2","size":1000,"edges":["netflix.tracing.zone1.MovieReviewDB0"]},
{"name":"netflix.tracing.zone1.mongodb_movieReview2","size":1000,"edges":["netflix.tracing.zone1.MovieReviewDB0"]},
{"name":"netflix.tracing.zone1.memcached_userReview2","size":1000,"edges":["netflix.tracing.zone1.UserReviewDB0"]},
{"name":"netflix.tracing.zone1.mongodb_userReview2","size":1000,"edges":["netflix.tracing.zone1.UserReviewDB0"]},
{"name":"netflix.tracing.zone1.memcached_movieInfo3","size":1000,"edges":["netflix.tracing.zone1.UpdateMovieInfo0"]},
{"name":"netflix.tracing.zone1.mongodb_movieInfo3","size":1000,"edges":["netflix.tracing.zone1.UpdateMovieInfo0"]},
{"name":"netflix.tracing.zone1.memcached_movieDB3","size":1000,"edges":["netflix.tracing.zone1.VideoPlayer0"]},
{"name":"netflix.tracing.zone1.mongodb_movieDB3","size":1000,"edges":["netflix.tracing.zone1.VideoPlayer0"]},
{"name":"netflix.tracing.zone1.memcached_movieReview3","size":1000,"edges":["netflix.tracing.zone1.MovieReviewDB0"]},
{"name":"netflix.tracing.zone1.mongodb_movieReview3","size":1000,"edges":["netflix.tracing.zone1.MovieReviewDB0"]},
{"name":"netflix.tracing.zone1.memcached_userReview3","size":1000,"edges":["netflix.tracing.zone1.UserReviewDB0"]},
{"name":"netflix.tracing.zone1.mongodb_userReview3","size":1000,"edges":["netflix.tracing.zone1.UserReviewDB0"]},
{"name":"netflix.tracing.zone1.memcached_movieInfo4","size":1000,"edges":["netflix.tracing.zone1.UpdateMovieInfo0"]},
{"name":"netflix.tracing.zone1.mongodb_movieInfo4","size":1000,"edges":["netflix.tracing.zone1.UpdateMovieInfo0"]},
{"name":"netflix.tracing.zone1.memcached_movieDB4","size":1000,"edges":["netflix.tracing.zone1.VideoPlayer0"]},
{"name":"netflix.tracing.zone1.mongodb_movieDB4","size":1000,"edges":["netflix.tracing.zone1.VideoPlayer0"]},
{"name":"netflix.tracing.zone1.memcached_movieReview4","size":1000,"edges":["netflix.tracing.zone1.MovieReviewDB0"]},
{"name":"netflix.tracing.zone1.mongodb_movieReview4","size":1000,"edges":["netflix.tracing.zone1.MovieReviewDB0"]},
{"name":"netflix.tracing.zone1.memcached_userReview4","size":1000,"edges":["netflix.tracing.zone1.UserReviewDB0"]},
{"name":"netflix.tracing.zone1.mongodb_userReview4","size":1000,"edges":["netflix.tracing.zone1.UserReviewDB0"]},
{"name":"netflix.tracing.zone1.memcached_movieInfo5","size":1000,"edges":["netflix.tracing.zone1.UpdateMovieInfo0"]},
{"name":"netflix.tracing.zone1.mongodb_movieInfo5","size":1000,"edges":["netflix.tracing.zone1.UpdateMovieInfo0"]},
{"name":"netflix.tracing.zone1.memcached_movieDB5","size":1000,"edges":["netflix.tracing.zone1.VideoPlayer0"]},
{"name":"netflix.tracing.zone1.mongodb_movieDB5","size":1000,"edges":["netflix.tracing.zone1.VideoPlayer0"]},
{"name":"netflix.tracing.zone1.memcached_movieReview5","size":1000,"edges":["netflix.tracing.zone1.MovieReviewDB0"]},
{"name":"netflix.tracing.zone1.mongodb_movieReview5","size":1000,"edges":["netflix.tracing.zone1.MovieReviewDB0"]},
{"name":"netflix.tracing.zone1.memcached_userReview5","size":1000,"edges":["netflix.tracing.zone1.UserReviewDB0"]},
{"name":"netflix.tracing.zone1.mongodb_userReview5","size":1000,"edges":["netflix.tracing.zone1.UserReviewDB0"]},
{"name":"netflix.tracing.zone1.memcached_movieInfo6","size":1000,"edges":["netflix.tracing.zone1.UpdateMovieInfo0"]},
{"name":"netflix.tracing.zone1.mongodb_movieInfo6","size":1000,"edges":["netflix.tracing.zone1.UpdateMovieInfo0"]},
{"name":"netflix.tracing.zone1.memcached_movieDB6","size":1000,"edges":["netflix.tracing.zone1.VideoPlayer0"]},
{"name":"netflix.tracing.zone1.mongodb_movieDB6","size":1000,"edges":["netflix.tracing.zone1.VideoPlayer0"]},
{"name":"netflix.tracing.zone1.memcached_movieReview6","size":1000,"edges":["netflix.tracing.zone1.MovieReviewDB0"]},
{"name":"netflix.tracing.zone1.mongodb_movieReview6","size":1000,"edges":["netflix.tracing.zone1.MovieReviewDB0"]},
{"name":"netflix.tracing.zone1.memcached_userReview6","size":1000,"edges":["netflix.tracing.zone1.UserReviewDB0"]},
{"name":"netflix.tracing.zone1.mongodb_userReview6","size":1000,"edges":["netflix.tracing.zone1.UserReviewDB0"]},
{"name":"netflix.tracing.zone1.memcached_movieInfo7","size":1000,"edges":["netflix.tracing.zone1.UpdateMovieInfo0"]},
{"name":"netflix.tracing.zone1.mongodb_movieInfo7","size":1000,"edges":["netflix.tracing.zone1.UpdateMovieInfo0"]},
{"name":"netflix.tracing.zone1.memcached_movieDB7","size":1000,"edges":["netflix.tracing.zone1.VideoPlayer0"]},
{"name":"netflix.tracing.zone1.mongodb_movieDB7","size":1000,"edges":["netflix.tracing.zone1.VideoPlayer0"]},
{"name":"netflix.tracing.zone1.memcached_movieReview7","size":1000,"edges":["netflix.tracing.zone1.MovieReviewDB0"]},
{"name":"netflix.tracing.zone1.mongodb_movieReview7","size":1000,"edges":["netflix.tracing.zone1.MovieReviewDB0"]},
{"name":"netflix.tracing.zone1.memcached_userReview7","size":1000,"edges":["netflix.tracing.zone1.UserReviewDB0"]},
{"name":"netflix.tracing.zone1.mongodb_userReview7","size":1000,"edges":["netflix.tracing.zone1.UserReviewDB0"]},
{"name":"netflix.tracing.zone1.memcached_movieInfo8","size":1000,"edges":["netflix.tracing.zone1.UpdateMovieInfo0"]},
{"name":"netflix.tracing.zone1.mongodb_movieInfo8","size":1000,"edges":["netflix.tracing.zone1.UpdateMovieInfo0"]},
{"name":"netflix.tracing.zone1.memcached_movieDB8","size":1000,"edges":["netflix.tracing.zone1.VideoPlayer0"]},
{"name":"netflix.tracing.zone1.mongodb_movieDB8","size":1000,"edges":["netflix.tracing.zone1.VideoPlayer0"]},
{"name":"netflix.tracing.zone1.memcached_movieReview8","size":1000,"edges":["netflix.tracing.zone1.MovieReviewDB0"]},
{"name":"netflix.tracing.zone1.mongodb_movieReview8","size":1000,"edges":["netflix.tracing.zone1.MovieReviewDB0"]},
{"name":"netflix.tracing.zone1.memcached_userReview8","size":1000,"edges":["netflix.tracing.zone1.UserReviewDB0"]},
{"name":"netflix.tracing.zone1.mongodb_userReview8","size":1000,"edges":["netflix.tracing.zone1.UserReviewDB0"]},
{"name":"netflix.tracing.zone1.memcached_movieInfo9","size":1000,"edges":["netflix.tracing.zone1.UpdateMovieInfo0"]},
{"name":"netflix.tracing.zone1.mongodb_movieInfo9","size":1000,"edges":["netflix.tracing.zone1.UpdateMovieInfo0"]},
{"name":"netflix.tracing.zone1.memcached_movieDB9","size":1000,"edges":["netflix.tracing.zone1.VideoPlayer0"]},
{"name":"netflix.tracing.zone1.mongodb_movieDB9","size":1000,"edges":["netflix.tracing.zone1.VideoPlayer0"]},
{"name":"netflix.tracing.zone1.memcached_movieReview9","size":1000,"edges":["netflix.tracing.zone1.MovieReviewDB0"]},
{"name":"netflix.tracing.zone1.mongodb_movieReview9","size":1000,"edges":["netflix.tracing.zone1.MovieReviewDB0"]},
{"name":"netflix.tracing.zone1.memcached_userReview9","size":1000,"edges":["netflix.tracing.zone1.UserReviewDB0"]},
{"name":"netflix.tracing.zone1.mongodb_userReview9","size":1000,"edges":["netflix.tracing.zone1.UserReviewDB0"]},
{"name":"netflix.tracing.zone2.memcached_movieInfo0","size":1000,"edges":["netflix.tracing.zone2.UpdateMovieInfo0"]},
{"name":"netflix.tracing.zone2.mongodb_movieInfo0","size":1000,"edges":["netflix.tracing.zone2.UpdateMovieInfo0"]},
{"name":"netflix.tracing.zone2.memcached_movieDB0","size":1000,"edges":["netflix.tracing.zone2.VideoPlayer0"]},
{"name":"netflix.tracing.zone2.mongodb_movieDB0","size":1000,"edges":["netflix.tracing.zone2.VideoPlayer0"]},
{"name":"netflix.tracing.zone2.memcached_movieReview0","size":1000,"edges":["netflix.tracing.zone2.MovieReviewDB0"]},
{"name":"netflix.tracing.zone2.mongodb_movieReview0","size":1000,"edges":["netflix.tracing.zone2.MovieReviewDB0"]},
{"name":"netflix.tracing.zone2.memcached_userReview0","size":1000,"edges":["netflix.tracing.zone2.UserReviewDB0"]},
{"name":"netflix.tracing.zone2.mongodb_userReview0","size":1000,"edges":["netflix.tracing.zone2.UserReviewDB0"]},
{"name":"netflix.tracing.zone2.memcached_movieInfo1","size":1000,"edges":["netflix.tracing.zone2.UpdateMovieInfo0"]},
{"name":"netflix.tracing.zone2.mongodb_movieInfo1","size":1000,"edges":["netflix.tracing.zone2.UpdateMovieInfo0"]},
{"name":"netflix.tracing.zone2.memcached_movieDB1","size":1000,"edges":["netflix.tracing.zone2.VideoPlayer0"]},
{"name":"netflix.tracing.zone2.mongodb_movieDB1","size":1000,"edges":["netflix.tracing.zone2.VideoPlayer0"]},
{"name":"netflix.tracing.zone2.memcached_movieReview1","size":1000,"edges":["netflix.tracing.zone2.MovieReviewDB0"]},
{"name":"netflix.tracing.zone2.mongodb_movieReview1","size":1000,"edges":["netflix.tracing.zone2.MovieReviewDB0"]},
{"name":"netflix.tracing.zone2.memcached_userReview1","size":1000,"edges":["netflix.tracing.zone2.UserReviewDB0"]},
{"name":"netflix.tracing.zone2.mongodb_userReview1","size":1000,"edges":["netflix.tracing.zone2.UserReviewDB0"]},
{"name":"netflix.tracing.zone2.memcached_movieInfo2","size":1000,"edges":["netflix.tracing.zone2.UpdateMovieInfo0"]},
{"name":"netflix.tracing.zone2.mongodb_movieInfo2","size":1000,"edges":["netflix.tracing.zone2.UpdateMovieInfo0"]},
{"name":"netflix.tracing.zone2.memcached_movieDB2","size":1000,"edges":["netflix.tracing.zone2.VideoPlayer0"]},
{"name":"netflix.tracing.zone2.mongodb_movieDB2","size":1000,"edges":["netflix.tracing.zone2.VideoPlayer0"]},
{"name":"netflix.tracing.zone2.memcached_movieReview2","size":1000,"edges":["netflix.tracing.zone2.MovieReviewDB0"]},
{"name":"netflix.tracing.zone2.mongodb_movieReview2","size":1000,"edges":["netflix.tracing.zone2.MovieReviewDB0"]},
{"name":"netflix.tracing.zone2.memcached_userReview2","size":1000,"edges":["netflix.tracing.zone2.UserReviewDB0"]},
{"name":"netflix.tracing.zone2.mongodb_userReview2","size":1000,"edges":["netflix.tracing.zone2.UserReviewDB0"]},
{"name":"netflix.tracing.zone2.memcached_movieInfo3","size":1000,"edges":["netflix.tracing.zone2.UpdateMovieInfo0"]},
{"name":"netflix.tracing.zone2.mongodb_movieInfo3","size":1000,"edges":["netflix.tracing.zone2.UpdateMovieInfo0"]},
{"name":"netflix.tracing.zone2.memcached_movieDB3","size":1000,"edges":["netflix.tracing.zone2.VideoPlayer0"]},
{"name":"netflix.tracing.zone2.mongodb_movieDB3","size":1000,"edges":["netflix.tracing.zone2.VideoPlayer0"]},
{"name":"netflix.tracing.zone2.memcached_movieReview3","size":1000,"edges":["netflix.tracing.zone2.MovieReviewDB0"]},
{"name":"netflix.tracing.zone2.mongodb_movieReview3","size":1000,"edges":["netflix.tracing.zone2.MovieReviewDB0"]},
{"name":"netflix.tracing.zone2.memcached_userReview3","size":1000,"edges":["netflix.tracing.zone2.UserReviewDB0"]},
{"name":"netflix.tracing.zone2.mongodb_userReview3","size":1000,"edges":["netflix.tracing.zone2.UserReviewDB0"]},
{"name":"netflix.tracing.zone2.memcached_movieInfo4","size":1000,"edges":["netflix.tracing.zone2.UpdateMovieInfo0"]},
{"name":"netflix.tracing.zone2.mongodb_movieInfo4","size":1000,"edges":["netflix.tracing.zone2.UpdateMovieInfo0"]},
{"name":"netflix.tracing.zone2.memcached_movieDB4","size":1000,"edges":["netflix.tracing.zone2.VideoPlayer0"]},
{"name":"netflix.tracing.zone2.mongodb_movieDB4","size":1000,"edges":["netflix.tracing.zone2.VideoPlayer0"]},
{"name":"netflix.tracing.zone2.memcached_movieReview4","size":1000,"edges":["netflix.tracing.zone2.MovieReviewDB0"]},
{"name":"netflix.tracing.zone2.mongodb_movieReview4","size":1000,"edges":["netflix.tracing.zone2.MovieReviewDB0"]},
{"name":"netflix.tracing.zone2.memcached_userReview4","size":1000,"edges":["netflix.tracing.zone2.UserReviewDB0"]},
{"name":"netflix.tracing.zone2.mongodb_userReview4","size":1000,"edges":["netflix.tracing.zone2.UserReviewDB0"]},
{"name":"netflix.tracing.zone2.memcached_movieInfo5","size":1000,"edges":["netflix.tracing.zone2.UpdateMovieInfo0"]},
{"name":"netflix.tracing.zone2.mongodb_movieInfo5","size":1000,"edges":["netflix.tracing.zone2.UpdateMovieInfo0"]},
{"name":"netflix.tracing.zone2.memcached_movieDB5","size":1000,"edges":["netflix.tracing.zone2.VideoPlayer0"]},
{"name":"netflix.tracing.zone2.mongodb_movieDB5","size":1000,"edges":["netflix.tracing.zone2.VideoPlayer0"]},
{"name":"netflix.tracing.zone2.memcached_movieReview5","size":1000,"edges":["netflix.tracing.zone2.MovieReviewDB0"]},
{"name":"netflix.tracing.zone2.mongodb_movieReview5","size":1000,"edges":["netflix.tracing.zone2.MovieReviewDB0"]},
{"name":"netflix.tracing.zone2.memcached_userReview5","size":1000,"edges":["netflix.tracing.zone2.UserReviewDB0"]},
{"name":"netflix.tracing.zone2.mongodb_userReview5","size":1000,"edges":["netflix.tracing.zone2.UserReviewDB0"]},
{"name":"netflix.tracing.zone2.memcached_movieInfo6","size":1000,"edges":["netflix.tracing.zone2.UpdateMovieInfo0"]},
{"name":"netflix.tracing.zone2.mongodb_movieInfo6","size":1000,"edges":["netflix.tracing.zone2.UpdateMovieInfo0"]},
{"name":"netflix.tracing.zone2.memcached_movieDB6","size":1000,"edges":["netflix.tracing.zone2.VideoPlayer0"]},
{"name":"netflix.tracing.zone2.mongodb_movieDB6","size":1000,"edges":["netflix.tracing.zone2.VideoPlayer0"]},
{"name":"netflix.tracing.zone2.memcached_movieReview6","size":1000,"edges":["netflix.tracing.zone2.MovieReviewDB0"]},
{"name":"netflix.tracing.zone2.mongodb_movieReview6","size":1000,"edges":["netflix.tracing.zone2.MovieReviewDB0"]},
{"name":"netflix.tracing.zone2.memcached_userReview6","size":1000,"edges":["netflix.tracing.zone2.UserReviewDB0"]},
{"name":"netflix.tracing.zone2.mongodb_userReview6","size":1000,"edges":["netflix.tracing.zone2.UserReviewDB0"]},
{"name":"netflix.tracing.zone2.memcached_movieInfo7","size":1000,"edges":["netflix.tracing.zone2.UpdateMovieInfo0"]},
{"name":"netflix.tracing.zone2.mongodb_movieInfo7","size":1000,"edges":["netflix.tracing.zone2.UpdateMovieInfo0"]},
{"name":"netflix.tracing.zone2.memcached_movieDB7","size":1000,"edges":["netflix.tracing.zone2.VideoPlayer0"]},
{"name":"netflix.tracing.zone2.mongodb_movieDB7","size":1000,"edges":["netflix.tracing.zone2.VideoPlayer0"]},
{"name":"netflix.tracing.zone2.memcached_movieReview7","size":1000,"edges":["netflix.tracing.zone2.MovieReviewDB0"]},
{"name":"netflix.tracing.zone2.mongodb_movieReview7","size":1000,"edges":["netflix.tracing.zone2.MovieReviewDB0"]},
{"name":"netflix.tracing.zone2.memcached_userReview7","size":1000,"edges":["netflix.tracing.zone2.UserReviewDB0"]},
{"name":"netflix.tracing.zone2.mongodb_userReview7","size":1000,"edges":["netflix.tracing.zone2.UserReviewDB0"]},
{"name":"netflix.tracing.zone2.memcached_movieInfo8","size":1000,"edges":["netflix.tracing.zone2.UpdateMovieInfo0"]},
{"name":"netflix.tracing.zone2.mongodb_movieInfo8","size":1000,"edges":["netflix.tracing.zone2.UpdateMovieInfo0"]},
{"name":"netflix.tracing.zone2.memcached_movieDB8","size":1000,"edges":["netflix.tracing.zone2.VideoPlayer0"]},
{"name":"netflix.tracing.zone2.mongodb_movieDB8","size":1000,"edges":["netflix.tracing.zone2.VideoPlayer0"]},
{"name":"netflix.tracing.zone2.memcached_movieReview8","size":1000,"edges":["netflix.tracing.zone2.MovieReviewDB0"]},
{"name":"netflix.tracing.zone2.mongodb_movieReview8","size":1000,"edges":["netflix.tracing.zone2.MovieReviewDB0"]},
{"name":"netflix.tracing.zone2.memcached_userReview8","size":1000,"edges":["netflix.tracing.zone2.UserReviewDB0"]},
{"name":"netflix.tracing.zone2.mongodb_userReview8","size":1000,"edges":["netflix.tracing.zone2.UserReviewDB0"]},
{"name":"netflix.tracing.zone2.memcached_movieInfo9","size":1000,"edges":["netflix.tracing.zone2.UpdateMovieInfo0"]},
{"name":"netflix.tracing.zone2.mongodb_movieInfo9","size":1000,"edges":["netflix.tracing.zone2.UpdateMovieInfo0"]},
{"name":"netflix.tracing.zone2.memcached_movieDB9","size":1000,"edges":["netflix.tracing.zone2.VideoPlayer0"]},
{"name":"netflix.tracing.zone2.mongodb_movieDB9","size":1000,"edges":["netflix.tracing.zone2.VideoPlayer0"]},
{"name":"netflix.tracing.zone2.memcached_movieReview9","size":1000,"edges":["netflix.tracing.zone2.MovieReviewDB0"]},
{"name":"netflix.tracing.zone2.mongodb_movieReview9","size":1000,"edges":["netflix.tracing.zone2.MovieReviewDB0"]},
{"name":"netflix.tracing.zone2.memcached_userReview9","size":1000,"edges":["netflix.tracing.zone2.UserReviewDB0"]},
{"name":"netflix.tracing.zone2.mongodb_userReview9","size":1000,"edges":["netflix.tracing.zone2.UserReviewDB0"]}
]
